amqp_api_client_py/__init__.py
amqp_api_client_py/amqp_input_api.py
amqp_api_client_py/amqp_output_api.py
amqp_api_client_py/config.py
amqp_api_client_py-0.2.2.dist-info/LICENSE
amqp_api_client_py-0.2.2.dist-info/METADATA
amqp_api_client_py-0.2.2.dist-info/WHEEL
amqp_api_client_py-0.2.2.dist-info/top_level.txt
amqp_api_client_py-0.2.2.dist-info/RECORD
