Metadata-Version: 2.1
Name: amqp-api-client-py
Version: 0.2.2
Summary: Basic AMQP client for API testing purposes
Author: aio_pika's developers
Author-email: Gabriel Amihalachioaie <gabriel@simpleg.eu>
Project-URL: Homepage, https://github.com/simple0x47/amqp-api-client-py
Classifier: Programming Language :: Python :: 3
Classifier: License :: OSI Approved :: MIT License
Classifier: Operating System :: OS Independent
Requires-Python: >=3.9
License-File: LICENSE
